AUTHORS
CHANGELOG.txt
DESCRIPTION
LICENSE
MANIFEST.in
setup.py
django_object_attachments.egg-info/PKG-INFO
django_object_attachments.egg-info/SOURCES.txt
django_object_attachments.egg-info/dependency_links.txt
django_object_attachments.egg-info/top_level.txt
object_attachments/__init__.py
object_attachments/admin.py
object_attachments/models.py
object_attachments/migrations/0001_initial.py
object_attachments/migrations/__init__.py
object_attachments/tests/__init__.py
object_attachments/tests/factories.py
object_attachments/tests/models_tests.py
object_attachments/tests/runtests.py
object_attachments/tests/south_settings.py
object_attachments/tests/test_settings.py
object_attachments/tests/urls.py
object_attachments/tests/test_app/__init__.py
object_attachments/tests/test_app/models.py
object_attachments/tests/test_app/templates/base.html
object_attachments/tests/test_app/templates/standard.html