Metadata-Version: 1.0
Name: django-object-attachments
Version: 0.1
Summary: Allows to add django-document-library objects to a any other object.
